{
	"name": "RideFixer_DataWarehouse_LinkedService",
	"properties": {
		"annotations": [],
		"type": "AzureSqlDW",
		"typeProperties": {
			"connectionString": "Integrated Security=False;Encrypt=True;Connection Timeout=30;Data Source=ridefixr-synapse-dev.sql.azuresynapse.net;Initial Catalog=RideFixrDataWarehouse;User ID=ridefixr_warehouse_user",
			"password": {
				"type": "AzureKeyVaultSecret",
				"store": {
					"referenceName": "RideFixr_KeyVault_LinkedService",
					"type": "LinkedServiceReference"
				},
				"secretName": "datawarehouse-key"
			}
		}
	}
}